CHANGELOG.md
MANIFEST.in
README.rst
setup.cfg
setup.py
rattail_harvest/__init__.py
rattail_harvest/_version.py
rattail_harvest/commands.py
rattail_harvest/config.py
rattail_harvest.egg-info/PKG-INFO
rattail_harvest.egg-info/SOURCES.txt
rattail_harvest.egg-info/dependency_links.txt
rattail_harvest.egg-info/entry_points.txt
rattail_harvest.egg-info/requires.txt
rattail_harvest.egg-info/top_level.txt
rattail_harvest/db/__init__.py
rattail_harvest/db/alembic/versions/53c066772ad5_rename_cache_tables.py
rattail_harvest/db/alembic/versions/5505c0e60d28_add_project_deleted.py
rattail_harvest/db/alembic/versions/6bc1cb21d920_add_harvest_user_person.py
rattail_harvest/db/alembic/versions/a1cf300fb371_fix_indeces.py
rattail_harvest/db/alembic/versions/d59ce24c2f9f_initial_harvest_tables.py
rattail_harvest/db/alembic/versions/f2a1650e7fbc_grow_id_fields.py
rattail_harvest/db/model/__init__.py
rattail_harvest/db/model/harvest.py
rattail_harvest/harvest/__init__.py
rattail_harvest/harvest/config.py
rattail_harvest/harvest/webapi.py
rattail_harvest/harvest/importing/__init__.py
rattail_harvest/harvest/importing/model.py
rattail_harvest/importing/__init__.py
rattail_harvest/importing/harvest.py
rattail_harvest/importing/model.py
rattail_harvest/importing/rattail.py
rattail_harvest/importing/versions.py