Metadata-Version: 2.1
Name: rattail-harvest
Version: 0.2.1
Summary: Rattail integration package for Harvest
Home-page: https://rattailproject.org/
Author: Lance Edgar
Author-email: lance@edbob.org
Classifier: Development Status :: 3 - Alpha
Classifier: Environment :: Console
Classifier: Intended Audience :: Developers
Classifier: License :: OSI Approved :: GNU General Public License v3 or later (GPLv3+)
Classifier: Natural Language :: English
Classifier: Operating System :: OS Independent
Classifier: Programming Language :: Python
Classifier: Programming Language :: Python :: 3
Classifier: Topic :: Office/Business
Classifier: Topic :: Software Development :: Libraries :: Python Modules
Requires-Dist: invoke
Requires-Dist: rattail[db]
